esi_utils_time/__init__.py
esi_utils_time/ancient_time.py
esi_utils_time/timeutils.py
esi_utils_time/data/combined-raster-with-oceans002.tif
esi_utils_time/data/country-time-codes.json
esi_utils_time/data/ne_10m_time_zones.README.html
esi_utils_time/data/ne_10m_time_zones.VERSION.txt
esi_utils_time/data/ne_10m_time_zones.cpg
esi_utils_time/data/ne_10m_time_zones.dbf
esi_utils_time/data/ne_10m_time_zones.prj
esi_utils_time/data/ne_10m_time_zones.shp
esi_utils_time/data/ne_10m_time_zones.shx
esi_utils_time-1.0.4.dist-info/licenses/LICENSE.md
esi_utils_time-1.0.4.dist-info/METADATA
esi_utils_time-1.0.4.dist-info/WHEEL
esi_utils_time-1.0.4.dist-info/top_level.txt
esi_utils_time-1.0.4.dist-info/RECORD
