Metadata-Version: 2.4
Name: esi-utils-time
Version: 1.0.4
Summary: USGS time utilities
Home-page: https://code.usgs.gov/ghsc/esi/esi-utils-time
Author: Mike Hearne
Author-email: Eric Thompson <emthompsone@usgs.gov>, Mike Hearne <mhearne@usgs.gov>
License: License
Requires-Python: >=3.9
License-File: LICENSE.md
Requires-Dist: beautifulsoup4>=4.11.0
Requires-Dist: numpy>=1.21
Requires-Dist: obspy>=1.4.1
Requires-Dist: pyproj>=3.7.0
Requires-Dist: pytz>=2024.1
Requires-Dist: fiona>=1.10.0
Requires-Dist: pillow>11.0.0
Requires-Dist: shapely>=2.0.5
Provides-Extra: dev
Requires-Dist: build>=0.7.0; extra == "dev"
Requires-Dist: black>=21; extra == "dev"
Requires-Dist: esi-releases>=0.1; extra == "dev"
Requires-Dist: flake8>=3.9; extra == "dev"
Requires-Dist: ipython>=7.26; extra == "dev"
Requires-Dist: pylint>=2.17; extra == "dev"
Provides-Extra: test
Requires-Dist: pytest>=6.2; extra == "test"
Requires-Dist: pytest-cov>=2.12; extra == "test"
Requires-Dist: pytest-console-scripts>=1.4; extra == "test"
Provides-Extra: build
Requires-Dist: build; extra == "build"
Requires-Dist: twine; extra == "build"
Requires-Dist: check-wheel-contents; extra == "build"
Dynamic: license-file
